aliyunsdkaddress_purification/__init__.py
aliyunsdkaddress_purification/endpoint.py
aliyunsdkaddress_purification/request/__init__.py
aliyunsdkaddress_purification/request/v20191118/ClassifyPOIRequest.py
aliyunsdkaddress_purification/request/v20191118/CompleteAddressRequest.py
aliyunsdkaddress_purification/request/v20191118/CorrectAddressRequest.py
aliyunsdkaddress_purification/request/v20191118/ExtractAddressRequest.py
aliyunsdkaddress_purification/request/v20191118/ExtractExpressRequest.py
aliyunsdkaddress_purification/request/v20191118/ExtractNameRequest.py
aliyunsdkaddress_purification/request/v20191118/ExtractPhoneRequest.py
aliyunsdkaddress_purification/request/v20191118/GetAddressBlockMappingRequest.py
aliyunsdkaddress_purification/request/v20191118/GetAddressDivisionCodeRequest.py
aliyunsdkaddress_purification/request/v20191118/GetAddressEvaluateRequest.py
aliyunsdkaddress_purification/request/v20191118/GetAddressGeocodeRequest.py
aliyunsdkaddress_purification/request/v20191118/GetAddressSearchRequest.py
aliyunsdkaddress_purification/request/v20191118/GetAddressSimilarityRequest.py
aliyunsdkaddress_purification/request/v20191118/GetInputSearchRequest.py
aliyunsdkaddress_purification/request/v20191118/GetZipcodeRequest.py
aliyunsdkaddress_purification/request/v20191118/PredictPOIRequest.py
aliyunsdkaddress_purification/request/v20191118/StructureAddressRequest.py
aliyunsdkaddress_purification/request/v20191118/TransferCoordRequest.py
aliyunsdkaddress_purification/request/v20191118/UpdateProjectRequest.py
aliyunsdkaddress_purification/request/v20191118/__init__.py
aliyun_python_sdk_address_purification-1.0.1.dist-info/LICENSE
aliyun_python_sdk_address_purification-1.0.1.dist-info/METADATA
aliyun_python_sdk_address_purification-1.0.1.dist-info/WHEEL
aliyun_python_sdk_address_purification-1.0.1.dist-info/top_level.txt
aliyun_python_sdk_address_purification-1.0.1.dist-info/RECORD
